README.md
setup.cfg
setup.py
pyvieslib/__init__.py
pyvieslib/pyvieslib.py
pyvieslib/vies_validator.py
pyvieslib.egg-info/PKG-INFO
pyvieslib.egg-info/SOURCES.txt
pyvieslib.egg-info/dependency_links.txt
pyvieslib.egg-info/top_level.txt