Metadata-Version: 2.1
Name: pyvieslib
Version: 0.8.0
Summary: Library for VIES number validation
Home-page: https://github.com/KG5321/pyvieslib
Author: KG5321
Author-email: konradgebler1@gmail.com
License: MIT
Download-URL: https://github.com/KG5321/pyvieslib/archive/0.5.tar.gz
Keywords: vies,nip,validation,eu,vat,number
Platform: UNKNOWN
Classifier: Development Status :: 3 - Alpha
Classifier: Intended Audience :: Developers
Classifier: Topic :: Software Development
Classifier: License :: OSI Approved :: MIT License
Classifier: Programming Language :: Python :: 3.8
